pri3o_dmenu_desktop/__init__.py
pri3o_dmenu_desktop/pri3o_dmenu_desktop.py
pri3o_dmenu_desktop-0.1.4.1.dist-info/LICENSE
pri3o_dmenu_desktop-0.1.4.1.dist-info/METADATA
pri3o_dmenu_desktop-0.1.4.1.dist-info/WHEEL
pri3o_dmenu_desktop-0.1.4.1.dist-info/entry_points.txt
pri3o_dmenu_desktop-0.1.4.1.dist-info/top_level.txt
pri3o_dmenu_desktop-0.1.4.1.dist-info/RECORD
