Metadata-Version: 2.1
Name: pri3o-dmenu-desktop
Version: 0.1.4.1
Summary: Drop-in replacement for i3-dmenu-desktop with simple app priorization 
Home-page: https://github.com/joe-batt/pri3o-dmenu-desktop
Author: Johannes Battenberg
Author-email: joe@chaoticneutral.eu
License: UNKNOWN
Platform: UNKNOWN
Classifier: License :: OSI Approved :: BSD License
Classifier: Operating System :: POSIX :: Linux
Classifier: Programming Language :: Python
Classifier: Programming Language :: Python :: 3
Classifier: Programming Language :: Python :: 3.5
Classifier: Programming Language :: Python :: 3.6
Classifier: Programming Language :: Python :: 3.7
Classifier: Programming Language :: Python :: 3.8
Classifier: Programming Language :: Python :: 3 :: Only
Requires-Python: >=3.5
